LICENSE
MANIFEST.in
README.md
setup.cfg
setup.py
confdir/__init__.py
confdir.egg-info/PKG-INFO
confdir.egg-info/SOURCES.txt
confdir.egg-info/dependency_links.txt
confdir.egg-info/top_level.txt